{
  "meta": {
    "agent": "daily-learner",
    "version": "1.0.0",
    "generated_at": "2026-03-22T23:00:02.126384+02:00",
    "duration_ms": 13,
    "ttl_hours": 24,
    "status": "success",
    "error": null,
    "run_id": "6474f856",
    "retries_used": 0,
    "data_freshness": "fresh"
  },
  "data": {
    "job_accuracy": {
      "total_recommendations": 254,
      "total_unique_jobs": 67,
      "submit_recommendations": 48,
      "applied_count": 18,
      "accuracy_rate": 37.5,
      "skip_candidates": [
        {
          "job_id": "linkedin-li-4379840970",
          "skip_signals": 3,
          "reason": "Business Engagement Director of Data & AI - data/AI engagement is somewhat technical; Director level fits but Data & AI is niche vs broad transformation"
        },
        {
          "job_id": "linkedin-li-4383479638",
          "skip_signals": 2,
          "reason": "Head of AI Strategy - strategic AI is adjacent to digital transformation but AI strategy is more niche/emerging tech vs broad programme leadership"
        },
        {
          "job_id": "google-in-bdeaee706e98c45c",
          "skip_signals": 2,
          "reason": "Head of Asset Management & AI Transformation is AI/asset-heavy; transformation is good but asset management domain is outside core FinTech/e-commerce/HealthTech"
        },
        {
          "job_id": "linkedin-li-4385663641",
          "skip_signals": 3,
          "reason": "CTO role in Dubai - technology executive but CTO is broader tech strategy vs digital transformation focus; Arabic speaker requirement"
        },
        {
          "job_id": "linkedin-li-4381045669",
          "skip_signals": 4,
          "reason": "CIO Private Markets - technology leadership in finance; C-suite level fits but private markets investment domain is slightly outside FinTech/payments core"
        },
        {
          "job_id": "linkedin-li-4377369566",
          "skip_signals": 3,
          "reason": "IT Head in KSA matches geography but general IT management is below executive DT level"
        },
        {
          "job_id": "linkedin-li-4384441676",
          "skip_signals": 3,
          "reason": "Senior Director level in target geography but Software Architecture is hands-on technical"
        },
        {
          "job_id": "linkedin-li-4174468962",
          "skip_signals": 2,
          "reason": "CEO at confidential company could fit but no domain signal - too speculative"
        },
        {
          "job_id": "linkedin-li-4374570926",
          "skip_signals": 2,
          "reason": "Head of IT at Dubai Smart City initiative has technology leadership angle but IT vs DT mismatch"
        }
      ]
    },
    "briefing_actionability": {
      "total_briefings": 0,
      "actionable_rate": null
    },
    "skip_patterns_added": [
      {
        "job_id": "linkedin-li-4385663641",
        "reason": "CTO role in Dubai - technology executive but CTO is broader tech strategy vs digital transformation focus; Arabic speaker requirement"
      },
      {
        "job_id": "linkedin-li-4174468962",
        "reason": "CEO at confidential company could fit but no domain signal - too speculative"
      },
      {
        "job_id": "linkedin-li-4374570926",
        "reason": "Head of IT at Dubai Smart City initiative has technology leadership angle but IT vs DT mismatch"
      }
    ],
    "weight_changes": [],
    "source_rankings": {
      "unknown": {
        "recommended": 254,
        "applied": 0,
        "rate": 0.0
      }
    },
    "summary": {
      "generated_at": "2026-03-22T23:00:02.125182+02:00",
      "period": "last_7_days",
      "job_recommendation_accuracy": {
        "rate": 37.5,
        "total": 254,
        "applied": 18
      },
      "briefing_actionability": {
        "total_briefings": 0,
        "changes_detected": false
      },
      "auto_adjustments": {
        "skip_patterns_added": 3,
        "weight_changes": 0,
        "source_rankings_updated": true
      },
      "insights": [
        "\u26a0\ufe0f Job recommendation accuracy low (38%) \u2014 weights adjusted",
        "\ud83d\udcdd Added 3 new skip patterns from feedback"
      ]
    }
  },
  "kpi": {
    "recommendation_accuracy": 37.5,
    "total_recommendations": 254,
    "skip_patterns_added": 3,
    "weight_changes": 0
  },
  "recommendations": []
}