{
  "meta": {
    "agent": "jobs-source-google",
    "version": "1.0.0",
    "generated_at": "2026-04-11T12:08:35.810602+02:00",
    "duration_ms": 512331,
    "ttl_hours": 6,
    "status": "success",
    "error": null,
    "run_id": "63050d2e",
    "retries_used": 0,
    "data_freshness": "fresh"
  },
  "data": [
    {
      "id": "google-a151c56b1b56",
      "source": "google",
      "title": "PMO Director",
      "company": "Confidential",
      "location": "Abu Dhabi, UAE",
      "url": "https://jobaaj.com/job/adasi-pmo-director-abu-dhabi-uae-5-to-7-years-891698",
      "posted": "",
      "seniority": "C-Suite",
      "domain_match": true,
      "keyword_score": 16,
      "match_keywords": [
        "pmo",
        "director"
      ],
      "raw_snippet": "",
      "relevant": true,
      "filter_reason": null
    }
  ],
  "kpi": {
    "searches_run": 107,
    "exa_results_raw": 668,
    "single_jobs_direct": 5,
    "listing_pages_found": 7,
    "listing_pages_extracted": 4,
    "noise_filtered": 471,
    "malformed_filtered": 24,
    "unique_jobs_final": 1,
    "errors": 0,
    "exa_cost_estimate_usd": 0.77,
    "strategy": "Exa keyword + auto(domain) + neural + watchlist company discovery \u2192 classify \u2192 GET_CONTENTS",
    "watchlist_companies": 33
  },
  "recommendations": []
}